netlistx/__init__.py
netlistx/cover.py
netlistx/graph_algo.py
netlistx/netlist.py
netlistx/netlist_algo.py
netlistx/skeleton.py
netlistx-0.2.dist-info/licenses/LICENSE.txt
netlistx-0.2.dist-info/METADATA
netlistx-0.2.dist-info/WHEEL
netlistx-0.2.dist-info/top_level.txt
netlistx-0.2.dist-info/RECORD
