Metadata-Version: 2.4
Name: netlistx
Version: 0.2
Summary: Ellipsoid Method in Python
Home-page: https://github.com/pyscaffold/pyscaffold/
Author: Wai-Shing Luk
Author-email: luk036@gmail.com
License: MIT
Project-URL: Documentation, https://pyscaffold.org/
Platform: any
Classifier: Development Status :: 4 - Beta
Classifier: Programming Language :: Python
License-File: LICENSE.txt
Requires-Dist: importlib-metadata; python_version < "3.9"
Requires-Dist: networkx
Provides-Extra: testing
Requires-Dist: setuptools; extra == "testing"
Requires-Dist: pytest; extra == "testing"
Requires-Dist: pytest-cov; extra == "testing"
Dynamic: license-file
